adder.sv
`timescale 1ns / 1ps
//==============================================================//
//  Module:       adder
//  File:         adder.sv
//  Description:  Generic paramaterized adder
//
//  Author:                     Viggo Wozniak
//  Reviewed/annotated by:      Patrick Pineda
//
//  Parameters:   WIDTH  - data width
//
//  Notes:        N/A
//==============================================================//

module adder #(
    parameter int WIDTH = 32
) (
    // data inputs
    input  logic [WIDTH-1:0] a,
    input  logic [WIDTH-1:0] b,

    // data outputs
    output logic [WIDTH-1:0] y
);

    assign y = a + b;

endmodule

flop.sv
`timescale 1ns / 1ps
//==============================================================//
//  Module:       flop
//  File:         flop.sv
//  Description:  Generic parameterized D flip-flop with reset
//
//  Author:       Patrrick P
//
//  Parameters:   WIDTH  - width of stored value
//
//  Notes:        Active-high synchronous reset
//==============================================================//
module flop #(
    parameter int WIDTH = 32
) (
    // Clock & control inputs
    input  logic             clk_i,
    input  logic             en,
    input  logic             reset,

    // data_i input
    input  logic [WIDTH-1:0] D,

    // data_i output
    output logic [WIDTH-1:0] Q
);

    always @(posedge clk_i) begin
        if      (reset) Q <= 0;
        else if (en)    Q <= D;
    end

endmodule

risc_top/pipelined_riscv_core/data_path/(1)fetch_stage/fetch_stage.sv
`timescale 1ns / 1ps
//==============================================================//
//  Module:       fetch_stage
//  File:         fetch_stage.sv
//  Description:  All logic contained within the fetch pipeline stage, along with its pipeline register
//
//  Author:                     Viggo Wozniak
//  Reviewed/annotated by:      Patrick Pineda
//  
//  DEPENDENCIES: flop.sv, adder.sv, control_macros.sv
//
//  Parameters:   Fetches next instruction
//==============================================================//
`include "../../../../../common/control_macros.sv"

module fetch_stage (
    // Clock & reset_i
    input  logic        clk_i,
    input  logic        reset_i,

    // Control inputs
    input  logic [1:0]  pc_src_i,               //where next PC comes from
    input  logic        stall_fi_i,             //freeze fetch (hazard/backpressure)

    // pc inputs
    input  logic [31:0] pc_target_ex_i,         // branch/jump target from ex stage
    input  logic [31:0] pc_plus4_ex_i,          // sequential PC (PC + 4) from ex stage
    input  logic [31:0] pred_pc_target_fi_i,    // prediction from branch predictor

    // pc outputs
    output logic [31:0] pc_fi_o,                // output PC
    output logic [31:0] pc_plus4_fi_o           // output PC + 4 (fetch stage output)
);

    // ---- Intermediate signal ----
    logic [31:0] pc_next_fi;

    //pc Register logic
    always_comb begin
        case(pc_src_i)
            `PC_SRC_SEQ_F:    pc_next_fi = pc_plus4_fi_o;       // from the adder
            `PC_SRC_PRED_F:   pc_next_fi = pred_pc_target_fi_i; // from branch predictor
            `PC_SRC_SEQ_E:    pc_next_fi = pc_plus4_ex_i;       // from ex stage
            `PC_SRC_TARGET_E: pc_next_fi = pc_target_ex_i;      // from ex stage
            default:          pc_next_fi = '0;
        endcase
    end

    flop u_pc_reg (
        // Clock & reset_i
        .clk_i                          (clk_i),
        .reset                          (reset_i),
        .en                             (~stall_fi_i),

        // data_i input
        .D                              (pc_next_fi),

        // data_i output
        .Q                              (pc_fi_o)
    );

    adder u_adder_pc_plus4 (
        // data_i inputs
        .a                              (pc_fi_o),
        .b                              (4),

        // data_i output
        .y                              (pc_plus4_fi_o)
    );

endmodule

risc_top/pipelined_riscv_core/data_path/(1) fetch_stage/tb/fetch_tb.sv
`timescale 1ns/1ps

`include "control_macros.sv"

// To run TB:
// iverilog -g2012 fetch_tb.sv ../fetch_stage.sv  -I ../../../../../common/ ../../../../../common/adder.sv ../../../../../common/flop.sv -o fetch_tb.out
// vvp fetch_tb.out
// gtkwave fetch_tb.vcd

module fetch_stage_tb;

    // -------------------------------------------------
    // DUT Signals
    // -------------------------------------------------
    logic        clk;
    logic        reset_i;

    logic [1:0]  pc_src_i;
    logic        stall_fi_i;

    logic [31:0] pc_target_ex_i;
    logic [31:0] pc_plus4_ex_i;
    logic [31:0] pred_pc_target_fi_i;

    logic [31:0] pc_fi_o;
    logic [31:0] pc_plus4_fi_o;

    // -------------------------------------------------
    // DUT Instance
    // -------------------------------------------------
    fetch_stage dut (
        .clk_i                  (clk),
        .reset_i                (reset_i),
        .pc_src_i               (pc_src_i),
        .stall_fi_i             (stall_fi_i),
        .pc_target_ex_i         (pc_target_ex_i),
        .pc_plus4_ex_i          (pc_plus4_ex_i),
        .pred_pc_target_fi_i    (pred_pc_target_fi_i),
        .pc_fi_o                (pc_fi_o),
        .pc_plus4_fi_o          (pc_plus4_fi_o)
    );

    // -------------------------------------------------
    // Clock Generation (10ns period)
    // -------------------------------------------------
    initial clk = 0;
    always #5 clk = ~clk;

    // -------------------------------------------------
    // Scoreboard tracking expected PC
    // -------------------------------------------------
    logic [31:0] expected_pc;

    task automatic check_pc();
        #1; // settle
        if (pc_fi_o !== expected_pc) begin
            $display("❌ ERROR @ %0t | expected: %h | got: %h",
                     $time, expected_pc, pc_fi_o);
            $fatal;
        end
        else begin
            $display("✅ PASS @ %0t | PC = %h",
                     $time, pc_fi_o);
        end
    endtask

    // -------------------------------------------------
    // Test Sequence
    // -------------------------------------------------
    initial begin
        $display("Starting fetch_stage test...");

        // Default values
        pc_src_i            = 2'b00;
        stall_fi_i          = 0;
        pc_target_ex_i      = 32'hAAAA_0000;
        pc_plus4_ex_i       = 32'hBBBB_0000;
        pred_pc_target_fi_i = 32'hCCCC_0000;

        // Reset (pc reg should be zero)
        reset_i = 1;
        repeat (2) @(posedge clk);
        reset_i = 0;

        // -----------------------------------------
        // 1. Sequential increments (PC + 4)
        // -----------------------------------------
        pc_src_i = `PC_SRC_SEQ_F;

        expected_pc = 32'h0000_0000;
        //@(posedge clk);                           ts breaks it!
        check_pc();

        repeat (2) begin
            expected_pc = expected_pc + 4;
            @(posedge clk);
            check_pc();
        end

        // -----------------------------------------
        // 2. Branch prediction source
        // -----------------------------------------
        pc_src_i = `PC_SRC_PRED_F;
        expected_pc = pred_pc_target_fi_i;
        @(posedge clk);
        check_pc();

        // -----------------------------------------
        // 3. EX sequential redirect
        // -----------------------------------------
        pc_src_i = `PC_SRC_SEQ_E;
        expected_pc = pc_plus4_ex_i;
        @(posedge clk);
        check_pc();

        // -----------------------------------------
        // 4. EX target redirect
        // -----------------------------------------
        pc_src_i = `PC_SRC_TARGET_E;
        expected_pc = pc_target_ex_i;
        @(posedge clk);
        check_pc();

        // -----------------------------------------
        // 5. Stall check (PC must not change)
        // -----------------------------------------
        pc_src_i   = `PC_SRC_SEQ_F;
        stall_fi_i = 1;

        @(posedge clk);
        #1;
        if (pc_fi_o !== expected_pc) begin
            $display("❌ ERROR: Stall failed!");
            $fatal;
        end
        else
            $display("✅ PASS: Stall held PC");

        stall_fi_i = 0;

        $display("All tests PASSED.");
        $finish;
    end

    initial begin
        $dumpfile("fetch_tb.vcd");           // Set VCD output filename
        $dumpvars(0, fetch_stage_tb);              // Dump all signals (level 0 = full hierarchy)
        $dumpvars(1, dut);                          // Explicitly dump DUT signals (redundant but safe)
    end

endmodule

risc_top/pipelined_riscv_core/data_path/(1)fetch_stage/tb/systemverilog/fetch_tb.vcd
$date
	Sat Feb 21 12:59:41 2026
$end
$version
	Icarus Verilog
$end
$timescale
	1ps
$end
$scope module fetch_stage_tb $end
$var wire 32 ! pc_plus4_fi_o [31:0] $end
$var wire 32 " pc_fi_o [31:0] $end
$var reg 1 # clk $end
$var reg 32 $ expected_pc [31:0] $end
$var reg 32 % pc_plus4_ex_i [31:0] $end
$var reg 2 & pc_src_i [1:0] $end
$var reg 32 ' pc_target_ex_i [31:0] $end
$var reg 32 ( pred_pc_target_fi_i [31:0] $end
$var reg 1 ) reset_i $end
$var reg 1 * stall_fi_i $end
$scope module dut $end
$var wire 1 # clk_i $end
$var wire 32 + pc_plus4_ex_i [31:0] $end
$var wire 2 , pc_src_i [1:0] $end
$var wire 32 - pc_target_ex_i [31:0] $end
$var wire 32 . pred_pc_target_fi_i [31:0] $end
$var wire 1 ) reset_i $end
$var wire 1 * stall_fi_i $end
$var wire 32 / pc_plus4_fi_o [31:0] $end
$var wire 32 0 pc_fi_o [31:0] $end
$var reg 32 1 pc_next_fi [31:0] $end
$scope module u_adder_pc_plus4 $end
$var wire 32 2 b [31:0] $end
$var wire 32 3 y [31:0] $end
$var wire 32 4 a [31:0] $end
$var parameter 32 5 WIDTH $end
$upscope $end
$scope module u_pc_reg $end
$var wire 32 6 D [31:0] $end
$var wire 1 # clk_i $end
$var wire 1 7 en $end
$var wire 1 ) reset $end
$var parameter 32 8 WIDTH $end
$var reg 32 9 Q [31:0] $end
$upscope $end
$upscope $end
$scope task check_pc $end
$upscope $end
$upscope $end
$scope module fetch_stage_tb $end
$scope module dut $end
$upscope $end
$upscope $end
$enddefinitions $end
$comment Show the parameter values. $end
$dumpall
b100000 8
b100000 5
$end
#0
$dumpvars
bx 9
17
bx 6
bx 4
bx 3
b100 2
bx 1
bx 0
bx /
b11001100110011000000000000000000 .
b10101010101010100000000000000000 -
b0 ,
b10111011101110110000000000000000 +
0*
1)
b11001100110011000000000000000000 (
b10101010101010100000000000000000 '
b0 &
b10111011101110110000000000000000 %
bx $
0#
bx "
bx !
$end
#5000
b100 1
b100 6
b100 !
b100 /
b100 3
b0 "
b0 0
b0 4
b0 9
1#
#10000
0#
#15000
b0 $
0)
1#
#16000
b100 $
#20000
0#
#25000
b1000 1
b1000 6
b1000 !
b1000 /
b1000 3
b100 "
b100 0
b100 4
b100 9
1#
#26000
b1000 $
#30000
0#
#35000
b1100 1
b1100 6
b1100 !
b1100 /
b1100 3
b1000 "
b1000 0
b1000 4
b1000 9
1#
#36000
b11001100110011000000000000000000 1
b11001100110011000000000000000000 6
b11001100110011000000000000000000 $
b1 &
b1 ,
#40000
0#
#45000
b11001100110011000000000000000100 !
b11001100110011000000000000000100 /
b11001100110011000000000000000100 3
b11001100110011000000000000000000 "
b11001100110011000000000000000000 0
b11001100110011000000000000000000 4
b11001100110011000000000000000000 9
1#
#46000
b10111011101110110000000000000000 1
b10111011101110110000000000000000 6
b10111011101110110000000000000000 $
b10 &
b10 ,
#50000
0#
#55000
b10111011101110110000000000000100 !
b10111011101110110000000000000100 /
b10111011101110110000000000000100 3
b10111011101110110000000000000000 "
b10111011101110110000000000000000 0
b10111011101110110000000000000000 4
b10111011101110110000000000000000 9
1#
#56000
b10101010101010100000000000000000 1
b10101010101010100000000000000000 6
b10101010101010100000000000000000 $
b11 &
b11 ,
#60000
0#
#65000
b10101010101010100000000000000100 !
b10101010101010100000000000000100 /
b10101010101010100000000000000100 3
b10101010101010100000000000000000 "
b10101010101010100000000000000000 0
b10101010101010100000000000000000 4
b10101010101010100000000000000000 9
1#
#66000
07
b10101010101010100000000000000100 1
b10101010101010100000000000000100 6
1*
b0 &
b0 ,
#70000
0#
#75000
1#
#76000
17
0*
