adder.sv
`timescale 1ns / 1ps
//==============================================================//
//  Module:       adder
//  File:         adder.sv
//  Description:  Generic paramaterized adder
//
//  Author:                     Viggo Wozniak
//  Reviewed/annotated by:      Patrick Pineda
//
//  Parameters:   WIDTH  - data width
//
//  Notes:        N/A
//==============================================================//

module adder #(
    parameter int WIDTH = 32
) (
    // data inputs
    input  logic [WIDTH-1:0] a,
    input  logic [WIDTH-1:0] b,

    // data outputs
    output logic [WIDTH-1:0] y
);

    assign y = a + b;

endmodule

flop.sv
`timescale 1ns / 1ps
//==============================================================//
//  Module:       flop
//  File:         flop.sv
//  Description:  Generic parameterized D flip-flop with reset
//
//  Author:       Patrrick P
//
//  Parameters:   WIDTH  - width of stored value
//
//  Notes:        Active-high synchronous reset
//==============================================================//
module flop #(
    parameter int WIDTH = 32
) (
    // Clock & control inputs
    input  logic             clk_i,
    input  logic             en,
    input  logic             reset,

    // data_i input
    input  logic [WIDTH-1:0] D,

    // data_i output
    output logic [WIDTH-1:0] Q
);

    always @(posedge clk_i) begin
        if      (reset) Q <= 0;
        else if (en)    Q <= D;
    end

endmodule

risc_top/pipelined_riscv_core/data_path/(1)fetch_stage/fetch_stage.sv
`timescale 1ns / 1ps
//==============================================================//
//  Module:       fetch_stage
//  File:         fetch_stage.sv
//  Description:  All logic contained within the fetch pipeline stage, along with its pipeline register
//
//  Author:                     Viggo Wozniak
//  Reviewed/annotated by:      Patrick Pineda
//  
//  DEPENDENCIES: flop.sv, adder.sv, control_macros.sv
//
//  Parameters:   Fetches next instruction
//  COMPILE IN VIVADO: xvlog fetch_stage.sv -i ../../../../common/ -sv
//==============================================================//
`include "../../../../common/control_macros.sv"

module fetch_stage (
    // Clock & reset_i
    input  logic        clk_i,
    input  logic        reset_i,

    // Control inputs
    input  logic [1:0]  pc_src_i,               //where next PC comes from
    input  logic        stall_fi_i,             //freeze fetch (hazard/backpressure)

    // pc inputs
    input  logic [31:0] pc_target_ex_i,         // branch/jump target from ex stage
    input  logic [31:0] pc_plus4_ex_i,          // sequential PC (PC + 4) from ex stage
    input  logic [31:0] pred_pc_target_fi_i,    // prediction from branch predictor

    // pc outputs
    output logic [31:0] pc_fi_o,                // output PC
    output logic [31:0] pc_plus4_fi_o           // output PC + 4 (fetch stage output)
);

    // ---- Intermediate signal ----
    logic [31:0] pc_next_fi;

    //pc Register logic
    always_comb begin
        case(pc_src_i)
            `PC_SRC_SEQ_F:    pc_next_fi = pc_plus4_fi_o;       // from the adder
            `PC_SRC_PRED_F:   pc_next_fi = pred_pc_target_fi_i; // from branch predictor
            `PC_SRC_SEQ_E:    pc_next_fi = pc_plus4_ex_i;       // from ex stage
            `PC_SRC_TARGET_E: pc_next_fi = pc_target_ex_i;      // from ex stage
            default:          pc_next_fi = '0;
        endcase
    end

    flop u_pc_reg (
        // Clock & reset_i
        .clk_i                          (clk_i),
        .reset                          (reset_i),
        .en                             (~stall_fi_i),

        // data_i input
        .D                              (pc_next_fi),

        // data_i output
        .Q                              (pc_fi_o)
    );

    adder u_adder_pc_plus4 (
        // data_i inputs
        .a                              (pc_fi_o),
        .b                              (4),

        // data_i output
        .y                              (pc_plus4_fi_o)
    );

endmodule

risc_top/pipelined_riscv_core/data_path/(1)fetch_stage/tb/iverilog/waveform.vcd
$version Generated by VerilatedVcd $end
$timescale 1ps $end
 $scope module TOP $end
  $var wire 1 " clk_i $end
  $var wire 1 # reset_i $end
  $var wire 2 $ pc_src_i [1:0] $end
  $var wire 1 % stall_fi_i $end
  $var wire 32 & pc_target_ex_i [31:0] $end
  $var wire 32 ' pc_plus4_ex_i [31:0] $end
  $var wire 32 ( pred_pc_target_fi_i [31:0] $end
  $var wire 32 ) pc_fi_o [31:0] $end
  $var wire 32 * pc_plus4_fi_o [31:0] $end
  $scope module fetch_stage $end
   $var wire 1 " clk_i $end
   $var wire 1 # reset_i $end
   $var wire 2 $ pc_src_i [1:0] $end
   $var wire 1 % stall_fi_i $end
   $var wire 32 & pc_target_ex_i [31:0] $end
   $var wire 32 ' pc_plus4_ex_i [31:0] $end
   $var wire 32 ( pred_pc_target_fi_i [31:0] $end
   $var wire 32 ) pc_fi_o [31:0] $end
   $var wire 32 * pc_plus4_fi_o [31:0] $end
   $var wire 32 + pc_next_fi [31:0] $end
   $scope module u_adder_pc_plus4 $end
    $var wire 32 - WIDTH [31:0] $end
    $var wire 32 ) a [31:0] $end
    $var wire 32 . b [31:0] $end
    $var wire 32 * y [31:0] $end
   $upscope $end
   $scope module u_pc_reg $end
    $var wire 32 - WIDTH [31:0] $end
    $var wire 1 " clk_i $end
    $var wire 1 , en $end
    $var wire 1 # reset $end
    $var wire 32 + D [31:0] $end
    $var wire 32 ) Q [31:0] $end
   $upscope $end
  $upscope $end
 $upscope $end
$enddefinitions $end


#0
0"
1#
b00 $
0%
b00000000000000000000000000000000 &
b00000000000000000000000000000000 '
b00000000000000000000000000000000 (
b00000000000000000000000000000000 )
b00000000000000000000000000000100 *
b00000000000000000000000000000100 +
1,
b00000000000000000000000000100000 -
b00000000000000000000000000000100 .
#1
1"
#2
0"
#3
1"
#4
0"
#5
1"
#6
0"
#7
1"
#8
0"
#9
1"
#10
0"
0#
#11
1"
b00000000000000000000000000000100 )
b00000000000000000000000000001000 *
b00000000000000000000000000001000 +
#12
0"
#13
1"
b00000000000000000000000000001000 )
b00000000000000000000000000001100 *
b00000000000000000000000000001100 +
#14
0"
#15
1"
b00000000000000000000000000001100 )
b00000000000000000000000000010000 *
b00000000000000000000000000010000 +
#16
0"
#17
1"
b00000000000000000000000000010000 )
b00000000000000000000000000010100 *
b00000000000000000000000000010100 +
#18
0"
#19
1"
b00000000000000000000000000010100 )
b00000000000000000000000000011000 *
b00000000000000000000000000011000 +
#20
0"
#21
1"
b00000000000000000000000000011000 )
b00000000000000000000000000011100 *
b00000000000000000000000000011100 +
#22
0"
#23
1"
b00000000000000000000000000011100 )
b00000000000000000000000000100000 *
b00000000000000000000000000100000 +
#24
0"
#25
1"
b00000000000000000000000000100000 )
b00000000000000000000000000100100 *
b00000000000000000000000000100100 +
#26
0"
#27
1"
b00000000000000000000000000100100 )
b00000000000000000000000000101000 *
b00000000000000000000000000101000 +
#28
0"
#29
1"
b00000000000000000000000000101000 )
b00000000000000000000000000101100 *
b00000000000000000000000000101100 +
#30
0"
b01 $
b00000000000000000000001000000000 (
b00000000000000000000001000000000 +
#31
1"
b00000000000000000000001000000000 )
b00000000000000000000001000000100 *
#32
0"
b10 $
b00000000000000000000001100000000 '
b00000000000000000000001100000000 +
#33
1"
b00000000000000000000001100000000 )
b00000000000000000000001100000100 *
#34
0"
b11 $
b00000000000000000000010000000000 &
b00000000000000000000010000000000 +
#35
1"
b00000000000000000000010000000000 )
b00000000000000000000010000000100 *
#36
0"
b00 $
b00000000000000000000010000000100 +
#37
1"
b00000000000000000000010000000100 )
b00000000000000000000010000001000 *
b00000000000000000000010000001000 +
#38
0"
1%
0,
#39
1"
#40
0"
#41
1"
#42
0"
#43
1"
#44
0"
#45
1"
#46
0"
#47
1"
#48
0"
b01 $
b00000000000000000000000111000000 &
b00000000000000000000000110111000 '
b00000000000000000000001010100000 (
b00000000000000000000001010100000 +
#49
1"
#50
0"
b10 $
0%
b00000000000000000000000001100000 &
b00000000000000000000001110010000 '
b00000000000000000000000110011000 (
b00000000000000000000001110010000 +
1,
#51
1"
b00000000000000000000001110010000 )
b00000000000000000000001110010100 *
#52
0"
b00 $
1%
b00000000000000000000000001000100 &
b00000000000000000000000001101000 '
b00000000000000000000001100001100 (
b00000000000000000000001110010100 +
0,
#53
1"
#54
0"
b00000000000000000000001111111000 &
b00000000000000000000001001001000 '
b00000000000000000000001011101100 (
#55
1"
#56
0"
0%
b00000000000000000000001001110100 &
b00000000000000000000001001110100 '
b00000000000000000000000111101100 (
1,
#57
1"
b00000000000000000000001110010100 )
b00000000000000000000001110011000 *
b00000000000000000000001110011000 +
#58
0"
1%
b00000000000000000000001101110100 &
b00000000000000000000001011001000 '
b00000000000000000000000100111100 (
0,
#59
1"
#60
0"
b11 $
b00000000000000000000000011110000 &
b00000000000000000000001011001100 '
b00000000000000000000000011011000 (
b00000000000000000000000011110000 +
#61
1"
#62
0"
b00 $
b00000000000000000000001110100000 &
b00000000000000000000001111110000 '
b00000000000000000000000101001000 (
b00000000000000000000001110011000 +
#63
1"
#64
0"
b10 $
0%
b00000000000000000000000100010100 &
b00000000000000000000000101111100 '
b00000000000000000000001101001100 (
b00000000000000000000000101111100 +
1,
#65
1"
b00000000000000000000000101111100 )
b00000000000000000000000110000000 *
#66
0"
b01 $
1%
b00000000000000000000000011001000 &
b00000000000000000000000000011100 '
b00000000000000000000000101001000 (
b00000000000000000000000101001000 +
0,
#67
1"
#68
0"
b00000000000000000000000010001000 &
b00000000000000000000001000101100 '
b00000000000000000000000111100100 (
b00000000000000000000000111100100 +
#69
1"
#70
0"
b10 $
b00000000000000000000000001000000 &
b00000000000000000000000111101100 '
b00000000000000000000000101100100 (
b00000000000000000000000111101100 +
#71
1"
#72
0"
b11 $
0%
b00000000000000000000000010000100 &
b00000000000000000000001001110000 '
b00000000000000000000000111000100 (
b00000000000000000000000010000100 +
1,
#73
1"
b00000000000000000000000010000100 )
b00000000000000000000000010001000 *
#74
0"
b00000000000000000000001101111100 &
b00000000000000000000000011111100 '
b00000000000000000000000111110100 (
b00000000000000000000001101111100 +
#75
1"
b00000000000000000000001101111100 )
b00000000000000000000001110000000 *
#76
0"
b01 $
1%
b00000000000000000000000011010100 &
b00000000000000000000000111011000 '
b00000000000000000000001110110100 (
b00000000000000000000001110110100 +
0,
#77
1"
#78
0"
b00 $
b00000000000000000000001010110000 &
b00000000000000000000000011101000 '
b00000000000000000000001000011000 (
b00000000000000000000001110000000 +
#79
1"
#80
0"
b10 $
0%
b00000000000000000000000110001000 &
b00000000000000000000000010000100 '
b00000000000000000000001011001100 (
b00000000000000000000000010000100 +
1,
#81
1"
b00000000000000000000000010000100 )
b00000000000000000000000010001000 *
#82
0"
b11 $
1%
b00000000000000000000000101101000 &
b00000000000000000000001110101100 '
b00000000000000000000000011101000 (
b00000000000000000000000101101000 +
0,
#83
1"
#84
0"
b00000000000000000000001111100100 &
b00000000000000000000001101010000 '
b00000000000000000000001110011100 (
b00000000000000000000001111100100 +
#85
1"
#86
0"
b10 $
b00000000000000000000000110011100 &
b00000000000000000000000100100100 '
b00000000000000000000000110101000 (
b00000000000000000000000100100100 +
#87
1"
#88
0"
b00 $
0%
b00000000000000000000001111100000 &
b00000000000000000000000001101000 '
b00000000000000000000001111000100 (
b00000000000000000000000010001000 +
1,
#89
1"
b00000000000000000000000010001000 )
b00000000000000000000000010001100 *
b00000000000000000000000010001100 +
#90
0"
b01 $
b00000000000000000000000111000000 &
b00000000000000000000001001000100 '
b00000000000000000000000101110100 (
b00000000000000000000000101110100 +
#91
1"
b00000000000000000000000101110100 )
b00000000000000000000000101111000 *
#92
0"
b11 $
b00000000000000000000001000010100 &
b00000000000000000000000101100100 '
b00000000000000000000001011000100 (
b00000000000000000000001000010100 +
#93
1"
b00000000000000000000001000010100 )
b00000000000000000000001000011000 *
#94
0"
b00 $
b00000000000000000000000111000000 &
b00000000000000000000001001001000 '
b00000000000000000000000001111100 (
b00000000000000000000001000011000 +
#95
1"
b00000000000000000000001000011000 )
b00000000000000000000001000011100 *
b00000000000000000000001000011100 +
#96
0"
b10 $
1%
b00000000000000000000000110101000 &
b00000000000000000000001010001100 '
b00000000000000000000000001101000 (
b00000000000000000000001010001100 +
0,
#97
1"
#98
0"
b01 $
0%
b00000000000000000000000100010100 &
b00000000000000000000001011100100 '
b00000000000000000000000101011100 (
b00000000000000000000000101011100 +
1,
#99
1"
b00000000000000000000000101011100 )
b00000000000000000000000101100000 *
#100
0"
b00 $
1%
b00000000000000000000001101001000 &
b00000000000000000000001010100000 '
b00000000000000000000001011011100 (
b00000000000000000000000101100000 +
0,
#101
1"
#102
0"
b11 $
b00000000000000000000001101101000 &
b00000000000000000000000011001100 '
b00000000000000000000000001111000 (
b00000000000000000000001101101000 +
#103
1"
#104
0"
0%
b00000000000000000000001010111000 &
b00000000000000000000001011110000 '
b00000000000000000000001000001100 (
b00000000000000000000001010111000 +
1,
#105
1"
b00000000000000000000001010111000 )
b00000000000000000000001010111100 *
#106
0"
b00000000000000000000001011011100 &
b00000000000000000000001100111100 '
b00000000000000000000001000011000 (
b00000000000000000000001011011100 +
#107
1"
b00000000000000000000001011011100 )
b00000000000000000000001011100000 *
#108
0"
b00000000000000000000001100101100 &
b00000000000000000000000100000100 '
b00000000000000000000000001110100 (
b00000000000000000000001100101100 +
#109
1"
b00000000000000000000001100101100 )
b00000000000000000000001100110000 *
#110
0"
b01 $
1%
b00000000000000000000000010101100 &
b00000000000000000000000010101100 '
b00000000000000000000000100110000 (
b00000000000000000000000100110000 +
0,
#111
1"
#112
0"
b11 $
b00000000000000000000001110100100 &
b00000000000000000000000101010100 '
b00000000000000000000001000001100 (
b00000000000000000000001110100100 +
#113
1"
#114
0"
b01 $
0%
b00000000000000000000000001000000 &
b00000000000000000000000111101100 '
b00000000000000000000000100101100 (
b00000000000000000000000100101100 +
1,
#115
1"
b00000000000000000000000100101100 )
b00000000000000000000000100110000 *
#116
0"
b10 $
b00000000000000000000000111011000 &
b00000000000000000000001101110100 '
b00000000000000000000000110111000 (
b00000000000000000000001101110100 +
#117
1"
b00000000000000000000001101110100 )
b00000000000000000000001101111000 *
#118
0"
b01 $
b00000000000000000000000110001000 &
b00000000000000000000001011000100 '
b00000000000000000000000000110000 (
b00000000000000000000000000110000 +
#119
1"
b00000000000000000000000000110000 )
b00000000000000000000000000110100 *
#120
0"
b00 $
b00000000000000000000001000011000 &
b00000000000000000000001011001100 '
b00000000000000000000001100100100 (
b00000000000000000000000000110100 +
#121
1"
b00000000000000000000000000110100 )
b00000000000000000000000000111000 *
b00000000000000000000000000111000 +
#122
0"
b11 $
1%
b00000000000000000000000101110000 &
b00000000000000000000001100111100 '
b00000000000000000000001100010000 (
b00000000000000000000000101110000 +
0,
#123
1"
#124
0"
b00 $
0%
b00000000000000000000001001111100 &
b00000000000000000000001001001000 '
b00000000000000000000001010011100 (
b00000000000000000000000000111000 +
1,
#125
1"
b00000000000000000000000000111000 )
b00000000000000000000000000111100 *
b00000000000000000000000000111100 +
#126
0"
b10 $
1%
b00000000000000000000001011111100 &
b00000000000000000000000011001000 '
b00000000000000000000001010111000 (
b00000000000000000000000011001000 +
0,
#127
1"
#128
0"
0%
b00000000000000000000000110000000 &
b00000000000000000000001000000000 '
b00000000000000000000000011110100 (
b00000000000000000000001000000000 +
1,
#129
1"
b00000000000000000000001000000000 )
b00000000000000000000001000000100 *
#130
0"
b00000000000000000000000111101000 &
b00000000000000000000000011000000 '
b00000000000000000000000010101100 (
b00000000000000000000000011000000 +
#131
1"
b00000000000000000000000011000000 )
b00000000000000000000000011000100 *
#132
0"
b00000000000000000000001011001100 &
b00000000000000000000000000110000 '
b00000000000000000000001100101100 (
b00000000000000000000000000110000 +
#133
1"
b00000000000000000000000000110000 )
b00000000000000000000000000110100 *
#134
0"
b00 $
1%
b00000000000000000000000110010000 &
b00000000000000000000001101100100 '
b00000000000000000000000111111000 (
b00000000000000000000000000110100 +
0,
#135
1"
#136
0"
b00000000000000000000001101000000 &
b00000000000000000000001100011100 '
b00000000000000000000000001001100 (
#137
1"
#138
0"
b11 $
b00000000000000000000000100011000 &
b00000000000000000000000011011000 '
b00000000000000000000000001101100 (
b00000000000000000000000100011000 +
#139
1"
#140
0"
b00 $
b00000000000000000000000111110000 &
b00000000000000000000000101010000 '
b00000000000000000000001100000100 (
b00000000000000000000000000110100 +
#141
1"
#142
0"
b01 $
0%
b00000000000000000000000011101100 &
b00000000000000000000000011001100 '
b00000000000000000000000101001000 (
b00000000000000000000000101001000 +
1,
#143
1"
b00000000000000000000000101001000 )
b00000000000000000000000101001100 *
#144
0"
b10 $
1%
b00000000000000000000000110101000 &
b00000000000000000000000001100100 '
b00000000000000000000001100010100 (
b00000000000000000000000001100100 +
0,
#145
1"
#146
0"
0%
b00000000000000000000000111010100 &
b00000000000000000000001001101000 '
b00000000000000000000000110111100 (
b00000000000000000000001001101000 +
1,
#147
1"
b00000000000000000000001001101000 )
b00000000000000000000001001101100 *
#148
0"
b11 $
1%
b00000000000000000000001111000000 &
b00000000000000000000001100010000 '
b00000000000000000000001000101000 (
b00000000000000000000001111000000 +
0,
#149
1"
#150
0"
b00 $
b00000000000000000000000111010000 &
b00000000000000000000000100101000 '
b00000000000000000000000111001000 (
b00000000000000000000001001101100 +
#151
1"
#152
0"
b11 $
b00000000000000000000001011001100 &
b00000000000000000000000000101100 '
b00000000000000000000001001001100 (
b00000000000000000000001011001100 +
#153
1"
#154
0"
b00 $
b00000000000000000000001011011000 &
b00000000000000000000001011000000 '
b00000000000000000000001111100000 (
b00000000000000000000001001101100 +
#155
1"
#156
0"
0%
b00000000000000000000001011001000 &
b00000000000000000000000111001100 '
b00000000000000000000000011000000 (
1,
#157
1"
b00000000000000000000001001101100 )
b00000000000000000000001001110000 *
b00000000000000000000001001110000 +
#158
0"
b11 $
1%
b00000000000000000000001100011000 &
b00000000000000000000001110110000 '
b00000000000000000000000100001100 (
b00000000000000000000001100011000 +
0,
#159
1"
#160
0"
b01 $
0%
b00000000000000000000000000011000 &
b00000000000000000000000010010100 '
b00000000000000000000001010010000 (
b00000000000000000000001010010000 +
1,
#161
1"
b00000000000000000000001010010000 )
b00000000000000000000001010010100 *
#162
0"
1%
b00000000000000000000001101111100 &
b00000000000000000000000000010100 '
b00000000000000000000000111010000 (
b00000000000000000000000111010000 +
0,
#163
1"
#164
0"
0%
b00000000000000000000001011001100 &
b00000000000000000000000000010000 '
b00000000000000000000001010000000 (
b00000000000000000000001010000000 +
1,
#165
1"
b00000000000000000000001010000000 )
b00000000000000000000001010000100 *
#166
0"
b10 $
1%
b00000000000000000000000110010100 &
b00000000000000000000001111110000 '
b00000000000000000000000010100100 (
b00000000000000000000001111110000 +
0,
#167
1"
#168
0"
b01 $
b00000000000000000000000011111100 &
b00000000000000000000000000111100 '
b00000000000000000000000111100000 (
b00000000000000000000000111100000 +
#169
1"
#170
0"
b11 $
b00000000000000000000000010000100 &
b00000000000000000000000011010100 '
b00000000000000000000000111001100 (
b00000000000000000000000010000100 +
#171
1"
#172
0"
b00 $
0%
b00000000000000000000000101001100 &
b00000000000000000000000110101100 '
b00000000000000000000001001000000 (
b00000000000000000000001010000100 +
1,
#173
1"
b00000000000000000000001010000100 )
b00000000000000000000001010001000 *
b00000000000000000000001010001000 +
#174
0"
b11 $
b00000000000000000000001011100100 &
b00000000000000000000001101011100 '
b00000000000000000000000000000100 (
b00000000000000000000001011100100 +
#175
1"
b00000000000000000000001011100100 )
b00000000000000000000001011101000 *
#176
0"
b01 $
b00000000000000000000001001010100 &
b00000000000000000000001110000000 '
b00000000000000000000000010110100 (
b00000000000000000000000010110100 +
#177
1"
b00000000000000000000000010110100 )
b00000000000000000000000010111000 *
#178
0"
1%
b00000000000000000000001010011000 &
b00000000000000000000001001101000 '
b00000000000000000000000010001100 (
b00000000000000000000000010001100 +
0,
#179
1"
#180
0"
b11 $
0%
b00000000000000000000000010100000 &
b00000000000000000000000000111000 '
b00000000000000000000000000011100 (
b00000000000000000000000010100000 +
1,
#181
1"
b00000000000000000000000010100000 )
b00000000000000000000000010100100 *
#182
0"
b00 $
b00000000000000000000001000111000 &
b00000000000000000000001100000100 '
b00000000000000000000001011001100 (
b00000000000000000000000010100100 +
#183
1"
b00000000000000000000000010100100 )
b00000000000000000000000010101000 *
b00000000000000000000000010101000 +
#184
0"
b10 $
b00000000000000000000000001111000 &
b00000000000000000000000101010100 '
b00000000000000000000001001000100 (
b00000000000000000000000101010100 +
#185
1"
b00000000000000000000000101010100 )
b00000000000000000000000101011000 *
#186
0"
1%
b00000000000000000000001000110100 &
b00000000000000000000000110011100 '
b00000000000000000000000010010000 (
b00000000000000000000000110011100 +
0,
#187
1"
#188
0"
b00000000000000000000000100110000 &
b00000000000000000000000010001100 '
b00000000000000000000000111010100 (
b00000000000000000000000010001100 +
#189
1"
#190
0"
b01 $
b00000000000000000000001001110000 &
b00000000000000000000000001111100 '
b00000000000000000000001111001100 (
b00000000000000000000001111001100 +
#191
1"
#192
0"
b00 $
0%
b00000000000000000000001110101100 &
b00000000000000000000001110100000 '
b00000000000000000000001111110100 (
b00000000000000000000000101011000 +
1,
#193
1"
b00000000000000000000000101011000 )
b00000000000000000000000101011100 *
b00000000000000000000000101011100 +
#194
0"
b11 $
1%
b00000000000000000000000111101100 &
b00000000000000000000001000000100 '
b00000000000000000000000100101000 (
b00000000000000000000000111101100 +
0,
#195
1"
#196
0"
b10 $
b00000000000000000000000111000000 &
b00000000000000000000000100110000 '
b00000000000000000000001101100100 (
b00000000000000000000000100110000 +
#197
1"
#198
0"
b01 $
0%
b00000000000000000000000010011000 &
b00000000000000000000001000111000 '
b00000000000000000000000110001000 (
b00000000000000000000000110001000 +
1,
#199
1"
b00000000000000000000000110001000 )
b00000000000000000000000110001100 *
#200
0"
b10 $
b00000000000000000000001111011100 &
b00000000000000000000001001011000 '
b00000000000000000000000100000000 (
b00000000000000000000001001011000 +
#201
1"
b00000000000000000000001001011000 )
b00000000000000000000001001011100 *
#202
0"
b00 $
b00000000000000000000001001100100 &
b00000000000000000000000000100100 '
b00000000000000000000000010111100 (
b00000000000000000000001001011100 +
#203
1"
b00000000000000000000001001011100 )
b00000000000000000000001001100000 *
b00000000000000000000001001100000 +
#204
0"
1%
b00000000000000000000000001111000 &
b00000000000000000000000111100000 '
b00000000000000000000001011000100 (
0,
#205
1"
#206
0"
b11 $
b00000000000000000000000011101000 &
b00000000000000000000001001011000 '
b00000000000000000000001110110000 (
b00000000000000000000000011101000 +
#207
1"
#208
0"
b01 $
0%
b00000000000000000000000111000000 &
b00000000000000000000001111010100 '
b00000000000000000000000001000100 (
b00000000000000000000000001000100 +
1,
#209
1"
b00000000000000000000000001000100 )
b00000000000000000000000001001000 *
#210
0"
1%
b00000000000000000000000000101100 &
b00000000000000000000000110111100 '
b00000000000000000000001000010100 (
b00000000000000000000001000010100 +
0,
#211
1"
#212
0"
b00000000000000000000001010001000 &
b00000000000000000000000110010000 '
b00000000000000000000000100111100 (
b00000000000000000000000100111100 +
#213
1"
#214
0"
b10 $
b00000000000000000000000101111100 &
b00000000000000000000000111101100 '
b00000000000000000000001101101000 (
b00000000000000000000000111101100 +
#215
1"
#216
0"
b11 $
b00000000000000000000001010001100 &
b00000000000000000000001010110100 '
b00000000000000000000000111111100 (
b00000000000000000000001010001100 +
#217
1"
#218
0"
b00 $
0%
b00000000000000000000001110101000 &
b00000000000000000000001000111100 '
b00000000000000000000000101111000 (
b00000000000000000000000001001000 +
1,
#219
1"
b00000000000000000000000001001000 )
b00000000000000000000000001001100 *
b00000000000000000000000001001100 +
#220
0"
b11 $
b00000000000000000000000010001000 &
b00000000000000000000000100011100 '
b00000000000000000000000000100100 (
b00000000000000000000000010001000 +
#221
1"
b00000000000000000000000010001000 )
b00000000000000000000000010001100 *
#222
0"
b00000000000000000000000000000000 &
b00000000000000000000000011111100 '
b00000000000000000000001111111100 (
b00000000000000000000000000000000 +
#223
1"
b00000000000000000000000000000000 )
b00000000000000000000000000000100 *
#224
0"
b10 $
b00000000000000000000001011100000 &
b00000000000000000000000010100000 '
b00000000000000000000000001000100 (
b00000000000000000000000010100000 +
#225
1"
b00000000000000000000000010100000 )
b00000000000000000000000010100100 *
#226
0"
b11 $
b00000000000000000000001110001000 &
b00000000000000000000000110011100 '
b00000000000000000000001000010100 (
b00000000000000000000001110001000 +
#227
1"
b00000000000000000000001110001000 )
b00000000000000000000001110001100 *
#228
0"
b00 $
b00000000000000000000001000110000 &
b00000000000000000000000101111100 '
b00000000000000000000001010001100 (
b00000000000000000000001110001100 +
#229
1"
b00000000000000000000001110001100 )
b00000000000000000000001110010000 *
b00000000000000000000001110010000 +
#230
0"
1%
b00000000000000000000000110101100 &
b00000000000000000000001111011000 '
b00000000000000000000000100001000 (
0,
#231
1"
#232
0"
b01 $
b00000000000000000000000101011000 &
b00000000000000000000001110101100 '
b00000000000000000000000001010000 (
b00000000000000000000000001010000 +
#233
1"
#234
0"
b00 $
b00000000000000000000001010010000 &
b00000000000000000000000110000000 '
b00000000000000000000000101111000 (
b00000000000000000000001110010000 +
#235
1"
#236
0"
b11 $
0%
b00000000000000000000000000101000 &
b00000000000000000000000101101100 '
b00000000000000000000000000111000 (
b00000000000000000000000000101000 +
1,
#237
1"
b00000000000000000000000000101000 )
b00000000000000000000000000101100 *
#238
0"
1%
b00000000000000000000000001100000 &
b00000000000000000000001111110100 '
b00000000000000000000001100101000 (
b00000000000000000000000001100000 +
0,
#239
1"
#240
0"
b01 $
b00000000000000000000001100000000 &
b00000000000000000000000010101000 '
b00000000000000000000000001100000 (
#241
1"
#242
0"
b11 $
0%
b00000000000000000000001100110000 &
b00000000000000000000001100111000 '
b00000000000000000000000010110000 (
b00000000000000000000001100110000 +
1,
#243
1"
b00000000000000000000001100110000 )
b00000000000000000000001100110100 *
#244
0"
b10 $
1%
b00000000000000000000001111101000 &
b00000000000000000000000110010100 '
b00000000000000000000001000001000 (
b00000000000000000000000110010100 +
0,
#245
1"
#246
0"
b00000000000000000000001010000100 &
b00000000000000000000001011001100 '
b00000000000000000000000010010100 (
b00000000000000000000001011001100 +
#247
1"
#248
0"
b11 $
0%
b00000000000000000000000000110000 &
b00000000000000000000000000101000 '
b00000000000000000000001011001000 (
b00000000000000000000000000110000 +
1,
#249
1"
b00000000000000000000000000110000 )
b00000000000000000000000000110100 *
#250
0"
b10 $
1%
b00000000000000000000000001010100 &
b00000000000000000000000011001100 '
b00000000000000000000000010001100 (
b00000000000000000000000011001100 +
0,
#251
1"
#252
0"
b11 $
0%
b00000000000000000000001101110000 &
b00000000000000000000001001111100 '
b00000000000000000000001111101000 (
b00000000000000000000001101110000 +
1,
#253
1"
b00000000000000000000001101110000 )
b00000000000000000000001101110100 *
#254
0"
b01 $
b00000000000000000000000011000000 &
b00000000000000000000001100000100 '
b00000000000000000000001101000000 (
b00000000000000000000001101000000 +
#255
1"
b00000000000000000000001101000000 )
b00000000000000000000001101000100 *
#256
0"
1%
b00000000000000000000000110011100 &
b00000000000000000000000101011100 '
b00000000000000000000000011010000 (
b00000000000000000000000011010000 +
0,
#257
1"
#258
0"
b00000000000000000000001111100100 &
b00000000000000000000001000101100 '
b00000000000000000000000001100000 (
b00000000000000000000000001100000 +
#259
1"
#260
0"
b11 $
0%
b00000000000000000000000110111100 &
b00000000000000000000000010101100 '
b00000000000000000000001001010000 (
b00000000000000000000000110111100 +
1,
#261
1"
b00000000000000000000000110111100 )
b00000000000000000000000111000000 *
#262
0"
b01 $
1%
b00000000000000000000001011101000 &
b00000000000000000000000011011000 '
b00000000000000000000000111100000 (
b00000000000000000000000111100000 +
0,
#263
1"
#264
0"
b00000000000000000000000100100100 &
b00000000000000000000001011100100 '
b00000000000000000000001011010000 (
b00000000000000000000001011010000 +
#265
1"
#266
0"
b11 $
0%
b00000000000000000000001011011000 &
b00000000000000000000000111010000 '
b00000000000000000000000110111100 (
b00000000000000000000001011011000 +
1,
#267
1"
b00000000000000000000001011011000 )
b00000000000000000000001011011100 *
#268
0"
b10 $
1%
b00000000000000000000000011111100 &
b00000000000000000000001110110100 '
b00000000000000000000000010100000 (
b00000000000000000000001110110100 +
0,
#269
1"
#270
0"
b11 $
0%
b00000000000000000000001000110100 &
b00000000000000000000000110110100 '
b00000000000000000000000110000100 (
b00000000000000000000001000110100 +
1,
#271
1"
b00000000000000000000001000110100 )
b00000000000000000000001000111000 *
#272
0"
b10 $
b00000000000000000000001110110000 &
b00000000000000000000000001010100 '
b00000000000000000000001011011100 (
b00000000000000000000000001010100 +
#273
1"
b00000000000000000000000001010100 )
b00000000000000000000000001011000 *
#274
0"
b00 $
b00000000000000000000001111110000 &
b00000000000000000000000011101000 '
b00000000000000000000000110110000 (
b00000000000000000000000001011000 +
#275
1"
b00000000000000000000000001011000 )
b00000000000000000000000001011100 *
b00000000000000000000000001011100 +
#276
0"
b01 $
1%
b00000000000000000000001000000100 &
b00000000000000000000001011111000 '
b00000000000000000000001101000100 (
b00000000000000000000001101000100 +
0,
#277
1"
#278
0"
b00000000000000000000000111111100 &
b00000000000000000000001110101100 '
b00000000000000000000000111010100 (
b00000000000000000000000111010100 +
#279
1"
#280
0"
b11 $
b00000000000000000000000100011000 &
b00000000000000000000000010111000 '
b00000000000000000000000101111000 (
b00000000000000000000000100011000 +
#281
1"
#282
0"
b10 $
b00000000000000000000000011010000 &
b00000000000000000000001111110000 '
b00000000000000000000000000111000 (
b00000000000000000000001111110000 +
#283
1"
#284
0"
0%
b00000000000000000000001001101000 &
b00000000000000000000001000001000 '
b00000000000000000000001011011100 (
b00000000000000000000001000001000 +
1,
#285
1"
b00000000000000000000001000001000 )
b00000000000000000000001000001100 *
#286
0"
b01 $
b00000000000000000000001110110100 &
b00000000000000000000000100111000 '
b00000000000000000000000011110100 (
b00000000000000000000000011110100 +
#287
1"
b00000000000000000000000011110100 )
b00000000000000000000000011111000 *
#288
0"
1%
b00000000000000000000000101010000 &
b00000000000000000000001101101000 '
b00000000000000000000001000000100 (
b00000000000000000000001000000100 +
0,
#289
1"
#290
0"
b00000000000000000000001000001000 &
b00000000000000000000001010010100 '
b00000000000000000000001111101000 (
b00000000000000000000001111101000 +
#291
1"
#292
0"
b00 $
0%
b00000000000000000000000110101100 &
b00000000000000000000000011111000 '
b00000000000000000000001100001000 (
b00000000000000000000000011111000 +
1,
