adder.sv
`timescale 1ns / 1ps
//==============================================================//
//  Module:       adder
//  File:         adder.sv
//  Description:  Generic paramaterized adder
//
//  Author:                     Viggo Wozniak
//  Reviewed/annotated by:      Patrick Pineda
//
//  Parameters:   WIDTH  - data width
//
//  Notes:        N/A
//==============================================================//

module adder #(
    parameter int WIDTH = 32
) (
    // data inputs
    input  logic [WIDTH-1:0] a,
    input  logic [WIDTH-1:0] b,

    // data outputs
    output logic [WIDTH-1:0] y
);

    assign y = a + b;

endmodule

flop.sv
`timescale 1ns / 1ps
//==============================================================//
//  Module:       flop
//  File:         flop.sv
//  Description:  Generic parameterized D flip-flop with reset
//
//  Author:       Patrrick P
//
//  Parameters:   WIDTH  - width of stored value
//
//  Notes:        Active-high synchronous reset
//==============================================================//
module flop #(
    parameter int WIDTH = 32
) (
    // Clock & control inputs
    input  logic             clk_i,
    input  logic             en,
    input  logic             reset,

    // data_i input
    input  logic [WIDTH-1:0] D,

    // data_i output
    output logic [WIDTH-1:0] Q
);

    always @(posedge clk_i) begin
        if      (reset) Q <= 0;
        else if (en)    Q <= D;
    end

endmodule

risc_top/pipelined_riscv_core/data_path/(1)fetch_stage/fetch_stage.sv
`timescale 1ns / 1ps
//==============================================================//
//  Module:       fetch_stage
//  File:         fetch_stage.sv
//  Description:  All logic contained within the fetch pipeline stage, along with its pipeline register
//
//  Author:                     Viggo Wozniak
//  Reviewed/annotated by:      Patrick Pineda
//  
//  DEPENDENCIES: flop.sv, adder.sv, control_macros.sv
//
//  Parameters:   Fetches next instruction
//  COMPILE IN VIVADO: xvlog fetch_stage.sv -i ../../../../common/ -sv
//==============================================================//
`include "../../../../common/control_macros.sv"

module fetch_stage (
    // Clock & reset_i
    input  logic        clk_i,
    input  logic        reset_i,

    // Control inputs
    input  logic [1:0]  pc_src_i,               //where next PC comes from
    input  logic        stall_fi_i,             //freeze fetch (hazard/backpressure)

    // pc inputs
    input  logic [31:0] pc_target_ex_i,         // branch/jump target from ex stage
    input  logic [31:0] pc_plus4_ex_i,          // sequential PC (PC + 4) from ex stage
    input  logic [31:0] pred_pc_target_fi_i,    // prediction from branch predictor

    // pc outputs
    output logic [31:0] pc_fi_o,                // output PC
    output logic [31:0] pc_plus4_fi_o           // output PC + 4 (fetch stage output)
);

    // ---- Intermediate signal ----
    logic [31:0] pc_next_fi;

    //pc Register logic
    always_comb begin
        case(pc_src_i)
            `PC_SRC_SEQ_F:    pc_next_fi = pc_plus4_fi_o;       // from the adder
            `PC_SRC_PRED_F:   pc_next_fi = pred_pc_target_fi_i; // from branch predictor
            `PC_SRC_SEQ_E:    pc_next_fi = pc_plus4_ex_i;       // from ex stage
            `PC_SRC_TARGET_E: pc_next_fi = pc_target_ex_i;      // from ex stage
            default:          pc_next_fi = '0;
        endcase
    end

    flop u_pc_reg (
        // Clock & reset_i
        .clk_i                          (clk_i),
        .reset                          (reset_i),
        .en                             (~stall_fi_i),

        // data_i input
        .D                              (pc_next_fi),

        // data_i output
        .Q                              (pc_fi_o)
    );

    adder u_adder_pc_plus4 (
        // data_i inputs
        .a                              (pc_fi_o),
        .b                              (4),

        // data_i output
        .y                              (pc_plus4_fi_o)
    );

endmodule

risc_top/pipelined_riscv_core/data_path/(1)fetch_stage/tb/fetch_tb_modular.sv
`timescale 1ns/1ps

`include "control_macros.sv"

// To run TB:
// cd ../\(1)fetch_stage/tb
// iverilog -g2012 fetch_tb_modular.sv ../fetch_stage.sv  -I ../../../../../common/ ../../../../../common/adder.sv ../../../../../common/flop.sv -o fetch_tb_modular.out
// vvp fetch_tb_modular.out
// gtkwave fetch_tb_modular.vcd

//Stimulus Module
module fetch_stage_stimulus(
    output logic        clk_i,
    output logic        reset_i,
    output logic [1:0]  pc_src_i,
    output logic        stall_fi_i,
    output logic [31:0] pc_target_ex_i,
    output logic [31:0] pc_plus4_ex_i,
    output logic [31:0] pred_pc_target_fi_i
);

    // Clock
    initial clk_i = 0;
    always #10 clk_i = ~clk_i;

    // Drive sequence
    initial begin
        // Defaults
        pc_src_i            = `PC_SRC_SEQ_F;
        stall_fi_i          = 0;
        pc_target_ex_i      = 32'hAAAA_0000;
        pc_plus4_ex_i       = 32'hBBBB_0000;
        pred_pc_target_fi_i = 32'hCCCC_0000;

        // Reset
        reset_i = 1;
        repeat (2) @(posedge clk_i);
        reset_i = 0;

        // Sequential increments
        repeat (3) @(posedge clk_i);

        // Branch prediction
        pc_src_i = `PC_SRC_PRED_F;
        @(posedge clk_i);

        // EX sequential
        pc_src_i = `PC_SRC_SEQ_E;
        @(posedge clk_i);

        // EX target
        pc_src_i = `PC_SRC_TARGET_E;
        @(posedge clk_i);

        // Stall test
        pc_src_i   = `PC_SRC_SEQ_F;
        stall_fi_i = 1;
        @(posedge clk_i);
        stall_fi_i = 0;

        #20 $finish;
    end

endmodule

//Monitor process
module fetch_stage_monitor(
    input logic        clk_i,
    input logic        reset_i,
    input logic [1:0]  pc_src_i,
    input logic        stall_fi_i,
    input logic [31:0] pc_target_ex_i,
    input logic [31:0] pc_plus4_ex_i,
    input logic [31:0] pred_pc_target_fi_i,
    input logic [31:0] pc_fi_o,
    input logic [31:0] pc_plus4_fi_o
);

always @(posedge clk_i) begin
    $display("[MONITOR] t=%0t | src=%0d stall=%0d | pc=%h pc+4=%h",
        $time, pc_src_i, stall_fi_i, pc_fi_o, pc_plus4_fi_o);
end

endmodule

//Checker
module fetch_stage_checker(
    input logic        clk_i,
    input logic        reset_i,
    input logic [1:0]  pc_src_i,
    input logic        stall_fi_i,
    input logic [31:0] pc_target_ex_i,
    input logic [31:0] pc_plus4_ex_i,
    input logic [31:0] pred_pc_target_fi_i,
    input logic [31:0] pc_fi_o
);

    logic [31:0] expected_pc;

    always @(posedge clk_i) begin
        if (reset_i) begin
            expected_pc <= 32'd0;
        end
        else if (!stall_fi_i) begin
            case (pc_src_i)
                `PC_SRC_SEQ_F:    expected_pc <= expected_pc + 4;
                `PC_SRC_PRED_F:   expected_pc <= pred_pc_target_fi_i;
                `PC_SRC_SEQ_E:    expected_pc <= pc_plus4_ex_i;
                `PC_SRC_TARGET_E: expected_pc <= pc_target_ex_i;
            endcase
        end

        // Compare
        if (!reset_i) begin
            if (pc_fi_o !== expected_pc) begin
                $display("❌ ERROR @ %0t | expected=%h got=%h",
                         $time, expected_pc, pc_fi_o);
                $fatal;
            end
        end
    end
endmodule

module fetch_tb;

    logic clk_i;
    logic reset_i;
    logic [1:0]  pc_src_i;
    logic        stall_fi_i;
    logic [31:0] pc_target_ex_i;
    logic [31:0] pc_plus4_ex_i;
    logic [31:0] pred_pc_target_fi_i;
    logic [31:0] pc_fi_o;
    logic [31:0] pc_plus4_fi_o;

    fetch_stage_stimulus stim (.*);

    fetch_stage dut (
        .clk_i(clk_i),
        .reset_i(reset_i),
        .pc_src_i(pc_src_i),
        .stall_fi_i(stall_fi_i),
        .pc_target_ex_i(pc_target_ex_i),
        .pc_plus4_ex_i(pc_plus4_ex_i),
        .pred_pc_target_fi_i(pred_pc_target_fi_i),
        .pc_fi_o(pc_fi_o),
        .pc_plus4_fi_o(pc_plus4_fi_o)
    );

    fetch_stage_monitor mon (.*);

    fetch_stage_checker check (.*);

    initial begin
        $dumpfile("fetch_tb_modular.vcd");        
        $dumpvars(0, fetch_tb);             
        $dumpvars(1, dut);                         
    end

endmodule

risc_top/pipelined_riscv_core/data_path/(1)fetch_stage/tb/modular/fetch_tb_modular.vcd
$date
	Tue Feb 24 16:26:58 2026
$end
$version
	Icarus Verilog
$end
$timescale
	1ps
$end
$scope module fetch_tb $end
$var wire 1 ! stall_fi_i $end
$var wire 1 " reset_i $end
$var wire 32 # pred_pc_target_fi_i [31:0] $end
$var wire 32 $ pc_target_ex_i [31:0] $end
$var wire 2 % pc_src_i [1:0] $end
$var wire 32 & pc_plus4_fi_o [31:0] $end
$var wire 32 ' pc_plus4_ex_i [31:0] $end
$var wire 32 ( pc_fi_o [31:0] $end
$var wire 1 ) clk_i $end
$scope module check $end
$var wire 1 ! stall_fi_i $end
$var wire 1 " reset_i $end
$var wire 32 * pred_pc_target_fi_i [31:0] $end
$var wire 32 + pc_target_ex_i [31:0] $end
$var wire 2 , pc_src_i [1:0] $end
$var wire 32 - pc_plus4_ex_i [31:0] $end
$var wire 32 . pc_fi_o [31:0] $end
$var wire 1 ) clk_i $end
$var reg 32 / expected_pc [31:0] $end
$upscope $end
$scope module dut $end
$var wire 1 ! stall_fi_i $end
$var wire 1 " reset_i $end
$var wire 32 0 pred_pc_target_fi_i [31:0] $end
$var wire 32 1 pc_target_ex_i [31:0] $end
$var wire 2 2 pc_src_i [1:0] $end
$var wire 32 3 pc_plus4_fi_o [31:0] $end
$var wire 32 4 pc_plus4_ex_i [31:0] $end
$var wire 32 5 pc_fi_o [31:0] $end
$var wire 1 ) clk_i $end
$var reg 32 6 pc_next_fi [31:0] $end
$scope module u_adder_pc_plus4 $end
$var wire 32 7 b [31:0] $end
$var wire 32 8 y [31:0] $end
$var wire 32 9 a [31:0] $end
$var parameter 32 : WIDTH $end
$upscope $end
$scope module u_pc_reg $end
$var wire 32 ; D [31:0] $end
$var wire 1 < en $end
$var wire 1 " reset $end
$var wire 1 ) clk_i $end
$var parameter 32 = WIDTH $end
$var reg 32 > Q [31:0] $end
$upscope $end
$upscope $end
$scope module mon $end
$var wire 32 ? pc_fi_o [31:0] $end
$var wire 32 @ pc_plus4_fi_o [31:0] $end
$var wire 1 ! stall_fi_i $end
$var wire 1 " reset_i $end
$var wire 32 A pred_pc_target_fi_i [31:0] $end
$var wire 32 B pc_target_ex_i [31:0] $end
$var wire 2 C pc_src_i [1:0] $end
$var wire 32 D pc_plus4_ex_i [31:0] $end
$var wire 1 ) clk_i $end
$upscope $end
$scope module stim $end
$var reg 1 ) clk_i $end
$var reg 32 E pc_plus4_ex_i [31:0] $end
$var reg 2 F pc_src_i [1:0] $end
$var reg 32 G pc_target_ex_i [31:0] $end
$var reg 32 H pred_pc_target_fi_i [31:0] $end
$var reg 1 " reset_i $end
$var reg 1 ! stall_fi_i $end
$upscope $end
$upscope $end
$scope module fetch_tb $end
$scope module dut $end
$upscope $end
$upscope $end
$enddefinitions $end
$comment Show the parameter values. $end
$dumpall
b100000 =
b100000 :
$end
#0
$dumpvars
b11001100110011000000000000000000 H
b10101010101010100000000000000000 G
b0 F
b10111011101110110000000000000000 E
b10111011101110110000000000000000 D
b0 C
b10101010101010100000000000000000 B
b11001100110011000000000000000000 A
bx @
bx ?
bx >
1<
bx ;
bx 9
bx 8
b100 7
bx 6
bx 5
b10111011101110110000000000000000 4
bx 3
b0 2
b10101010101010100000000000000000 1
b11001100110011000000000000000000 0
bx /
bx .
b10111011101110110000000000000000 -
b0 ,
b10101010101010100000000000000000 +
b11001100110011000000000000000000 *
0)
bx (
b10111011101110110000000000000000 '
bx &
b0 %
b10101010101010100000000000000000 $
b11001100110011000000000000000000 #
1"
0!
$end
#10000
b100 6
b100 ;
b100 &
b100 3
b100 8
b100 @
b0 (
b0 .
b0 5
b0 9
b0 >
b0 ?
b0 /
1)
#20000
0)
#30000
b1000 6
b1000 ;
b100 /
b1000 &
b1000 3
b1000 8
b1000 @
b100 (
b100 .
b100 5
b100 9
b100 >
b100 ?
0"
1)
#40000
0)
#50000
b1100 6
b1100 ;
b1100 &
b1100 3
b1100 8
b1100 @
b1000 (
b1000 .
b1000 5
b1000 9
b1000 >
b1000 ?
b1000 /
1)
#60000
0)
#70000
b10000 6
b10000 ;
b1100 /
b10000 &
b10000 3
b10000 8
b10000 @
b1100 (
b1100 .
b1100 5
b1100 9
b1100 >
b1100 ?
1)
#80000
0)
#90000
b10100 &
b10100 3
b10100 8
b10100 @
b10000 (
b10000 .
b10000 5
b10000 9
b10000 >
b10000 ?
b10000 /
b11001100110011000000000000000000 6
b11001100110011000000000000000000 ;
b1 %
b1 ,
b1 2
b1 C
b1 F
1)
#100000
0)
#110000
b10111011101110110000000000000000 /
b11001100110011000000000000000100 &
b11001100110011000000000000000100 3
b11001100110011000000000000000100 8
b11001100110011000000000000000100 @
b11001100110011000000000000000000 (
b11001100110011000000000000000000 .
b11001100110011000000000000000000 5
b11001100110011000000000000000000 9
b11001100110011000000000000000000 >
b11001100110011000000000000000000 ?
b10111011101110110000000000000000 6
b10111011101110110000000000000000 ;
b10 %
b10 ,
b10 2
b10 C
b10 F
1)
#120000
0)
#130000
b10111011101110110000000000000100 &
b10111011101110110000000000000100 3
b10111011101110110000000000000100 8
b10111011101110110000000000000100 @
b10111011101110110000000000000000 (
b10111011101110110000000000000000 .
b10111011101110110000000000000000 5
b10111011101110110000000000000000 9
b10111011101110110000000000000000 >
b10111011101110110000000000000000 ?
b10101010101010100000000000000000 6
b10101010101010100000000000000000 ;
b11 %
b11 ,
b11 2
b11 C
b11 F
1)
